[{"id":"46b012eb.3634bc","type":"telegram sender","z":"d6bf7c08c7c5fdba","name":"","bot":"65ca12172854cc2d","haserroroutput":false,"outputs":1,"x":540,"y":80,"wires":[["dbe8656.f963498"]]},{"id":"edd05cdc.ccba7","type":"inject","z":"d6bf7c08c7c5fdba","name":"send csv string","props":[{"p":"payload"},{"p":"topic","vt":"str"}],"repeat":"","crontab":"","once":false,"onceDelay":"","topic":"","payload":"a, b, c, d","payloadType":"str","x":150,"y":80,"wires":[["62a75af3.7db694"]]},{"id":"62a75af3.7db694","type":"function","z":"d6bf7c08c7c5fdba","name":"send document","func":"var chatId = 138708568;\n\nvar doc = Buffer.from(msg.payload);\n\nvar fileOptions = {\n    filename : \"foo.csv\",\n    contentType : \"text/csv\"\n}\n\nvar payload = {\n    type: \"document\",\n    chatId: chatId,\n    content: doc,\n    fileOptions : fileOptions\n}\n\nmsg.payload = payload;\nreturn msg;","outputs":1,"timeout":"","noerr":0,"initialize":"","finalize":"","libs":[],"x":330,"y":80,"wires":[["46b012eb.3634bc"]]},{"id":"dbe8656.f963498","type":"debug","z":"d6bf7c08c7c5fdba","name":"","active":true,"tosidebar":true,"console":false,"tostatus":false,"complete":"false","statusVal":"","statusType":"auto","x":750,"y":80,"wires":[]},{"id":"65ca12172854cc2d","type":"telegram bot","botname":"HeinzBot","usernames":"","chatids":"","baseapiurl":"","testenvironment":false,"updatemode":"polling","addressfamily":"4","pollinterval":"1000","usesocks":false,"sockshost":"192.168.178.200","socksprotocol":"socks4","socksport":"1080","socksusername":"user","sockspassword":"password","bothost":"ihive.spdns.de","botpath":"","localbothost":"127.0.0.1","localbotport":"8443","publicbotport":"8443","privatekey":"","certificate":"","useselfsignedcertificate":false,"sslterminated":true,"verboselogging":false}]